setup.py
example_probability_distributions/Binomialdistribution.py
example_probability_distributions/Gaussiandistribution.py
example_probability_distributions/Generaldistribution.py
example_probability_distributions/__init__.py
example_probability_distributions.egg-info/PKG-INFO
example_probability_distributions.egg-info/SOURCES.txt
example_probability_distributions.egg-info/dependency_links.txt
example_probability_distributions.egg-info/not-zip-safe
example_probability_distributions.egg-info/top_level.txt