Metadata-Version: 1.0
Name: example-probability-distributions
Version: 0.1
Summary: Gaussian and Binomial distributions
Home-page: UNKNOWN
Author: Novak Zaballa
Author-email: zaballa.novak@gmail.com
License: UNKNOWN
Platform: UNKNOWN
